litellm/__init__.py
litellm/_logging.py
litellm/_redis.py
litellm/_service_logger.py
litellm/_uuid.py
litellm/_version.py
litellm/anthropic_interface/__init__.py
litellm/anthropic_interface/messages/__init__.py
litellm/anthropic_interface/readme.md
litellm/assistants/main.py
litellm/assistants/utils.py
litellm/batch_completion/Readme.md
litellm/batch_completion/main.py
litellm/batches/batch_utils.py
litellm/batches/main.py
litellm/budget_manager.py
litellm/caching/Readme.md
litellm/caching/__init__.py
litellm/caching/_internal_lru_cache.py
litellm/caching/azure_blob_cache.py
litellm/caching/base_cache.py
litellm/caching/caching.py
litellm/caching/caching_handler.py
litellm/caching/disk_cache.py
litellm/caching/dual_cache.py
litellm/caching/gcs_cache.py
litellm/caching/in_memory_cache.py
litellm/caching/llm_caching_handler.py
litellm/caching/qdrant_semantic_cache.py
litellm/caching/redis_cache.py
litellm/caching/redis_cluster_cache.py
litellm/caching/redis_semantic_cache.py
litellm/caching/s3_cache.py
litellm/completion_extras/README.md
litellm/completion_extras/__init__.py
litellm/completion_extras/litellm_responses_transformation/__init__.py
litellm/completion_extras/litellm_responses_transformation/handler.py
litellm/completion_extras/litellm_responses_transformation/transformation.py
litellm/constants.py
litellm/containers/__init__.py
litellm/containers/main.py
litellm/containers/utils.py
litellm/cost.json
litellm/cost_calculator.py
litellm/endpoints/speech/speech_to_completion_bridge/handler.py
litellm/endpoints/speech/speech_to_completion_bridge/transformation.py
litellm/exceptions.py
litellm/experimental_mcp_client/Readme.md
litellm/experimental_mcp_client/__init__.py
litellm/experimental_mcp_client/client.py
litellm/experimental_mcp_client/tools.py
litellm/files/main.py
litellm/files/utils.py
litellm/fine_tuning/main.py
litellm/google_genai/Readme.md
litellm/google_genai/__init__.py
litellm/google_genai/adapters/__init__.py
litellm-1.79.2.dist-info/LICENSE
litellm-1.79.2.dist-info/METADATA
litellm-1.79.2.dist-info/WHEEL
litellm-1.79.2.dist-info/entry_points.txt
litellm-1.79.2.dist-info/RECORD
